multi_manager_client/__init__.py
multi_manager_client/multi_manager_client.py
scramjet_multi_manager_client-1.1.0.dist-info/METADATA
scramjet_multi_manager_client-1.1.0.dist-info/WHEEL
scramjet_multi_manager_client-1.1.0.dist-info/top_level.txt
scramjet_multi_manager_client-1.1.0.dist-info/RECORD
